noregret/__init__.py
noregret/games.py
noregret/regret_minimizers.py
noregret/utilities.py
noregret-0.0.0.dev2.dist-info/licenses/LICENSE
noregret-0.0.0.dev2.dist-info/METADATA
noregret-0.0.0.dev2.dist-info/WHEEL
noregret-0.0.0.dev2.dist-info/top_level.txt
noregret-0.0.0.dev2.dist-info/RECORD
