Metadata-Version: 2.4
Name: noregret
Version: 0.0.0.dev2
Summary: No-regret learning dynamics
Home-page: https://github.com/uoftcprg/noregret
Author: Universal, Open, Free, and Transparent Computer Poker Research Group
Author-email: juhok@cs.cmu.edu
License: MIT
Project-URL: Documentation, https://noregret.readthedocs.io/en/latest/
Project-URL: Source, https://github.com/uoftcprg/noregret
Project-URL: Tracker, https://github.com/uoftcprg/noregret/issues
Keywords: artificial-intelligence,game,game-theory,imperfect-information-game,online-learning,python
Classifier: Intended Audience :: Developers
Classifier: Intended Audience :: Education
Classifier: Topic :: Education
Classifier: Topic :: Scientific/Engineering
Classifier: Topic :: Scientific/Engineering :: Artificial Intelligence
Classifier: License :: OSI Approved :: MIT License
Classifier: Operating System :: OS Independent
Classifier: Programming Language :: Python
Classifier: Programming Language :: Python :: 3
Classifier: Programming Language :: Python :: 3 :: Only
Classifier: Programming Language :: Python :: 3.11
Classifier: Programming Language :: Python :: 3.12
Classifier: Programming Language :: Python :: 3.13
Requires-Python: >=3.11
License-File: LICENSE
Requires-Dist: numpy<3,>=2.3.3
Requires-Dist: ordered-set<5,>=4.1.0
Requires-Dist: scipy<2,>=1.16.1
Dynamic: author
Dynamic: author-email
Dynamic: classifier
Dynamic: description
Dynamic: description-content-type
Dynamic: home-page
Dynamic: keywords
Dynamic: license
Dynamic: license-file
Dynamic: project-url
Dynamic: requires-dist
Dynamic: requires-python
Dynamic: summary
